{
    "members" : [
        {
        "name" : "Mana Vault",
        "address" : "3807 S Packard Ave Back Building, St Francis, WI 53235",
        "phone_number" : "(414) 763-9111",
        "url" : "https://www.facebook.com/p/The-Mana-Vault-MKE-100087482048156/",
        "img" : "images/mana_vault.webp",
        "level" : "Gold"
        },
        {
        "name" : "Mana Vault",
        "address" : "3807 S Packard Ave Back Building, St Francis, WI 53235",
        "phone_number" : "(414) 763-9111",
        "url" : "https://www.facebook.com/p/The-Mana-Vault-MKE-100087482048156/",
        "img" : "images/mana_vault.webp",
        "level" : "Gold"
        },
        {
        "name" : "Mana Vault",
        "address" : "3807 S Packard Ave Back Building, St Francis, WI 53235",
        "phone_number" : "(414) 763-9111",
        "url" : "https://www.facebook.com/p/The-Mana-Vault-MKE-100087482048156/",
        "img" : "images/mana_vault.webp",
        "level" : "Gold"
        },
        {
        "name" : "Mana Vault",
        "address" : "3807 S Packard Ave Back Building, St Francis, WI 53235",
        "phone_number" : "(414) 763-9111",
        "url" : "https://www.facebook.com/p/The-Mana-Vault-MKE-100087482048156/",
        "img" : "images/mana_vault.webp",
        "level" : "Gold"
        },
        {
        "name" : "Mana Vault",
        "address" : "3807 S Packard Ave Back Building, St Francis, WI 53235",
        "phone_number" : "(414) 763-9111",
        "url" : "https://www.facebook.com/p/The-Mana-Vault-MKE-100087482048156/",
        "img" : "images/mana_vault.webp",
        "level" : "Gold"
        }
        {
            "name" : "Mana Vault",
            "address" : "3807 S Packard Ave Back Building, St Francis, WI 53235",
            "phone_number" : "(414) 763-9111",
            "url" : "https://www.facebook.com/p/The-Mana-Vault-MKE-100087482048156/",
            "img" : "images/mana_vault.webp",
            "level" : "Gold"
          },
          {
            "name" : "Mana Vault",
            "address" : "3807 S Packard Ave Back Building, St Francis, WI 53235",
            "phone_number" : "(414) 763-9111",
            "url" : "https://www.facebook.com/p/The-Mana-Vault-MKE-100087482048156/",
            "img" : "images/mana_vault.webp",
            "level" : "Gold"
          },
          {
            "name" : "Mana Vault",
            "address" : "3807 S Packard Ave Back Building, St Francis, WI 53235",
            "phone_number" : "(414) 763-9111",
            "url" : "https://www.facebook.com/p/The-Mana-Vault-MKE-100087482048156/",
            "img" : "images/mana_vault.webp",
            "level" : "Gold"
          },
          {
            "name" : "Mana Vault",
            "address" : "3807 S Packard Ave Back Building, St Francis, WI 53235",
            "phone_number" : "(414) 763-9111",
            "url" : "https://www.facebook.com/p/The-Mana-Vault-MKE-100087482048156/",
            "img" : "images/mana_vault.webp",
            "level" : "Gold"
          },
    ]
}